setup.py
dividebatur/__init__.py
dividebatur/common.py
dividebatur/counter.py
dividebatur/results.py
dividebatur/senatecount.py
dividebatur.egg-info/PKG-INFO
dividebatur.egg-info/SOURCES.txt
dividebatur.egg-info/dependency_links.txt
dividebatur.egg-info/entry_points.txt
dividebatur.egg-info/requires.txt
dividebatur.egg-info/top_level.txt
dividebatur/aecdata/__init__.py
dividebatur/aecdata/candidatelist.py
dividebatur/aecdata/post2015.py
dividebatur/aecdata/pre2015.py
dividebatur/aecdata/utils.py