Metadata-Version: 1.0
Name: dividebatur
Version: 0.11.0
Summary: process single-transferable-vote elections as used for the Australian Senate under the Commonwealth Electoral Act (1918)
Home-page: https://github.com/grahame/dividebatur
Author: Grahame Bowland
Author-email: grahame@angrygoats.net
License: Apache2
Keywords: stv senate voting
Platform: UNKNOWN
